LICENSE
MANIFEST.in
README.rst
setup.py
django_extlog/__init__.py
django_extlog/admin.py
django_extlog/middleware.py
django_extlog/models.py
django_extlog.egg-info/PKG-INFO
django_extlog.egg-info/SOURCES.txt
django_extlog.egg-info/dependency_links.txt
django_extlog.egg-info/requires.txt
django_extlog.egg-info/top_level.txt