Metadata-Version: 1.1
Name: django-extlog
Version: 0.7
Summary: Extended log for Django, that tracks changes in models.
Home-page: https://github.com/AxiaCore/django-extlog
Author: Vera Mazhuga
Author-email: ctrl-alt-delete@live.ru
License: MIT
Platform: UNKNOWN
Classifier: Environment :: Web Environment
Classifier: Framework :: Django
Classifier: Intended Audience :: Developers
Classifier: Programming Language :: Python
